search_compiler/__init__.py
search_compiler/advanced_unitaries.py
search_compiler/assembler.py
search_compiler/checkpoint.py
search_compiler/circuits.py
search_compiler/compiler.py
search_compiler/gatesets.py
search_compiler/graphics.py
search_compiler/heuristics.py
search_compiler/logging.py
search_compiler/project.py
search_compiler/qasm_circuits.py
search_compiler/solver.py
search_compiler/unitaries.py
search_compiler/utils.py
search_compiler-1.2.1.dist-info/LICENSE
search_compiler-1.2.1.dist-info/METADATA
search_compiler-1.2.1.dist-info/WHEEL
search_compiler-1.2.1.dist-info/top_level.txt
search_compiler-1.2.1.dist-info/RECORD
