Metadata-Version: 2.1
Name: search-compiler
Version: 1.2.1
Summary: Search-Based Quantum Synthesis/Compilation
Home-page: UNKNOWN
Author: LBNL - AQT
Author-email: marc.davis@lbl.gov
License: UNKNOWN
Keywords: quantum compilers synthesis computing
Platform: UNKNOWN
Classifier: Development Status :: 4 - Beta
Classifier: Intended Audience :: Science/Research
Classifier: Topic :: Software Development :: Compilers
Classifier: Programming Language :: Python :: 3.6
Classifier: Programming Language :: Python :: 3.7
Classifier: Programming Language :: Python :: 3.8
Requires-Python: >=3.6, <4
Requires-Dist: numpy
Requires-Dist: scipy
Requires-Dist: scrs (>=0.6)
Provides-Extra: cma
Requires-Dist: cma ; extra == 'cma'
Provides-Extra: graphics
Requires-Dist: matplotlib ; extra == 'graphics'
